Metadata-Version: 1.0
Name: mf-distributions
Version: 0.1
Summary: Statistical distributions for Udacity
Home-page: UNKNOWN
Author: UNKNOWN
Author-email: UNKNOWN
License: UNKNOWN
Platform: UNKNOWN
